[
    {
        "id": 1,
        "name": "Real Madrid",
        "abbr": "RMA",
        "country": "Spain",
        "flag": "🇪🇸",
        "played": 8,
        "won": 6,
        "drawn": 1,
        "lost": 1,
        "points": 19,
        "goals": 18,
        "scorer": "Mbappé"
    },
    {
        "id": 2,
        "name": "Man City",
        "abbr": "MCI",
        "country": "England",
        "flag": "🏴󠁧󠁢󠁥󠁮󠁧󠁿",
        "played": 8,
        "won": 5,
        "drawn": 2,
        "lost": 1,
        "points": 17,
        "goals": 15,
        "scorer": "Haaland"
    },
    {
        "id": 3,
        "name": "Bayern Munich",
        "abbr": "BAY",
        "country": "Germany",
        "flag": "🇩🇪",
        "played": 8,
        "won": 5,
        "drawn": 1,
        "lost": 2,
        "points": 16,
        "goals": 16,
        "scorer": "Kane"
    },
    {
        "id": 4,
        "name": "Paris SG",
        "abbr": "PSG",
        "country": "France",
        "flag": "🇫🇷",
        "played": 8,
        "won": 5,
        "drawn": 0,
        "lost": 3,
        "points": 15,
        "goals": 14,
        "scorer": "Ramos"
    },
    {
        "id": 5,
        "name": "Barcelona",
        "abbr": "BAR",
        "country": "Spain",
        "flag": "🇪🇸",
        "played": 8,
        "won": 4,
        "drawn": 3,
        "lost": 1,
        "points": 15,
        "goals": 13,
        "scorer": "Lewandowski"
    },
    {
        "id": 6,
        "name": "Liverpool",
        "abbr": "LIV",
        "country": "England",
        "flag": "🏴󠁧󠁢󠁥󠁮󠁧󠁿",
        "played": 8,
        "won": 4,
        "drawn": 2,
        "lost": 2,
        "points": 14,
        "goals": 14,
        "scorer": "Salah"
    },
    {
        "id": 7,
        "name": "Inter Milan",
        "abbr": "INT",
        "country": "Italy",
        "flag": "🇮🇹",
        "played": 8,
        "won": 4,
        "drawn": 2,
        "lost": 2,
        "points": 14,
        "goals": 12,
        "scorer": "Martinez"
    },
    {
        "id": 8,
        "name": "Arsenal",
        "abbr": "ARS",
        "country": "England",
        "flag": "🏴󠁧󠁢󠁥󠁮󠁧󠁿",
        "played": 8,
        "won": 4,
        "drawn": 1,
        "lost": 3,
        "points": 13,
        "goals": 11,
        "scorer": "Saka"
    },
    {
        "id": 9,
        "name": "Atlético Madrid",
        "abbr": "ATM",
        "country": "Spain",
        "flag": "🇪🇸",
        "played": 8,
        "won": 4,
        "drawn": 1,
        "lost": 3,
        "points": 13,
        "goals": 10,
        "scorer": "Griezmann"
    },
    {
        "id": 10,
        "name": "Dortmund",
        "abbr": "BVB",
        "country": "Germany",
        "flag": "🇩🇪",
        "played": 8,
        "won": 3,
        "drawn": 3,
        "lost": 2,
        "points": 12,
        "goals": 13,
        "scorer": "Guirassy"
    },
    {
        "id": 11,
        "name": "Benfica",
        "abbr": "BEN",
        "country": "Portugal",
        "flag": "🇵🇹",
        "played": 8,
        "won": 3,
        "drawn": 2,
        "lost": 3,
        "points": 11,
        "goals": 10,
        "scorer": "Pavlidis"
    },
    {
        "id": 12,
        "name": "AC Milan",
        "abbr": "ACM",
        "country": "Italy",
        "flag": "🇮🇹",
        "played": 8,
        "won": 3,
        "drawn": 2,
        "lost": 3,
        "points": 11,
        "goals": 9,
        "scorer": "Leão"
    },
    {
        "id": 13,
        "name": "Napoli",
        "abbr": "NAP",
        "country": "Italy",
        "flag": "🇮🇹",
        "played": 8,
        "won": 3,
        "drawn": 1,
        "lost": 4,
        "points": 10,
        "goals": 11,
        "scorer": "Lukaku"
    },
    {
        "id": 14,
        "name": "RB Leipzig",
        "abbr": "RBL",
        "country": "Germany",
        "flag": "🇩🇪",
        "played": 8,
        "won": 3,
        "drawn": 1,
        "lost": 4,
        "points": 10,
        "goals": 9,
        "scorer": "Openda"
    },
    {
        "id": 15,
        "name": "Porto",
        "abbr": "POR",
        "country": "Portugal",
        "flag": "🇵🇹",
        "played": 8,
        "won": 2,
        "drawn": 3,
        "lost": 3,
        "points": 9,
        "goals": 9,
        "scorer": "Galeno"
    }
]